<?xml version="1.0" encoding="utf-8"?>
<Defs>

  <ThingDef ParentName="SkyfallerBase">
    <defName>SlagScatter</defName>
    <label>ship debris (incoming)</label>
		<thingClass>DropPodIncoming</thingClass>
    <graphicData>
      <texPath>Things/Sterile_slag</texPath>
      <graphicClass>Graphic_Random</graphicClass>
      <shaderType>CutoutFlying</shaderType>
      <drawSize>1.5</drawSize>
    </graphicData>
    <skyfaller>
      <shadow>Things/Skyfaller/SkyfallerShadowDropPod</shadow>
      <shadowSize>(2, 2)</shadowSize>
      <explosionRadius>1</explosionRadius>
      <explosionDamage>Bomb</explosionDamage>
      <explosionDamageFactor>0.25</explosionDamageFactor>
	  <cameraShake>1</cameraShake>
      <motesPerCell>0</motesPerCell>
    </skyfaller>
  </ThingDef>

	
</Defs>