<?xml version="1.0" encoding="utf-8"?>
<LanguageData>

  <ChunkSlagSteel.label>steel slag chunk</ChunkSlagSteel.label>
  <ChunkSlagSteel.description>A chunk of steel slag. While it's useless in its current form, it can be smelted to recover steel.</ChunkSlagSteel.description>

  <ChunkSlagSterile.label>sterile slag chunk</ChunkSlagSterile.label>
  <ChunkSlagSterile.description>A chunk of slag that appears to be from a sterile compartment of a ship. While it's useless in its current form, it can be smelted to recover silver and steel.</ChunkSlagSterile.description>

  <ChunkSlagGold.label>luxury slag chunk</ChunkSlagGold.label>
  <ChunkSlagGold.description>A chunk of slag that appears to be from some luxury compartment of a ship. While it's useless in its current form, it can be smelted to recover gold and steel.</ChunkSlagGold.description>

  <ChunkSlagPlasteel.label>plasteel slag chunk</ChunkSlagPlasteel.label>
  <ChunkSlagPlasteel.description>A chunk of plasteel slag. While it's useless in its current form, it can be smelted to recover plasteel.</ChunkSlagPlasteel.description>


</LanguageData>